gqlgen/__init__.py
gqlgen/generator.py
gqlgen/main.py
gqlgen/utils.py
gqlgen-0.0.7.dist-info/entry_points.txt
gqlgen-0.0.7.dist-info/LICENSE
gqlgen-0.0.7.dist-info/WHEEL
gqlgen-0.0.7.dist-info/METADATA
gqlgen-0.0.7.dist-info/RECORD
